LICENSE
MANIFEST.in
README.rst
setup.py
calfile/__init__.py
calfile/settings.py
calfile/tests.py
calfile/urls.py
calfile/utils.py
calfile/views.py
calfile/wsgi.py
django_calfile.egg-info/PKG-INFO
django_calfile.egg-info/SOURCES.txt
django_calfile.egg-info/dependency_links.txt
django_calfile.egg-info/requires.txt
django_calfile.egg-info/top_level.txt
docs/blank.txt